[
  {
    "id": "wnb_12101001_001",
    "mainTitle": "양사와 홍문관에서 조헌에게 죄주기를 청하다宣祖修正實錄 5책 22권宣祖修正實錄 25책",
    "date": "1588-01-01L0"
  },
  {
    "id": "wnb_12101001_002",
    "mainTitle": "경강의 물이 피처럼 붉은 지가 수일이 되다宣祖修正實錄 5책 22권宣祖修正實錄 25책",
    "date": "1588-01-01L0"
  },
  {
    "id": "wnb_12101001_003",
    "mainTitle": "북병사 이일이 녹도를 침입한 죄를 물어 추도를 습격하여 호인을 베다宣祖修正實錄 5책 22권宣祖修正實錄 25책",
    "date": "1588-01-01L0"
  },
  {
    "id": "wnb_12101001_004",
    "mainTitle": "권극지를 대사헌으로, 이해수를 충청 감사로, 이호민을 홍문관 수찬으로 삼다宣祖修正實錄 5책 22권宣祖修正實錄 25책",
    "date": "1588-01-01L0"
  },
  {
    "id": "wnb_12102001_001",
    "mainTitle": "사은사 유홍이 《대명회전》과 칙서를 받들고 경사에서 돌아오다宣祖修正實錄 5책 22권宣祖修正實錄 25책",
    "date": "1588-02-01L0"
  },
  {
    "id": "wnb_12102001_002",
    "mainTitle": "유홍의 품계를 숭록 대부에 초수하고 판부사에 제수하다宣祖修正實錄 5책 22권宣祖修正實錄 25책",
    "date": "1588-02-01L0"
  },
  {
    "id": "wnb_12102001_003",
    "mainTitle": "유홍을 예조 판서로 삼았다가 좌찬성으로 승진시키다宣祖修正實錄 5책 22권宣祖修正實錄 25책",
    "date": "1588-02-01L0"
  },
  {
    "id": "wnb_12103001_001",
    "mainTitle": "군신이 종계를 개정하고 전대의 공렬을 빛냈다는 것으로 존호 올리기를 청하다宣祖修正實錄 5책 22권宣祖修正實錄 25책",
    "date": "1588-03-01L0"
  },
  {
    "id": "wnb_12103001_002",
    "mainTitle": "관각의 제신에게 주사 마유명의 시의 운에 화답하는 시를 지어 올리게 하다宣祖修正實錄 5책 22권宣祖修正實錄 25책",
    "date": "1588-03-01L0"
  },
  {
    "id": "wnb_12103001_003",
    "mainTitle": "식년 전시에서 김시헌 등 33인을 뽑다宣祖修正實錄 5책 22권宣祖修正實錄 25책",
    "date": "1588-03-01L0"
  },
  {
    "id": "wnb_12104001_001",
    "mainTitle": "영의정 노수신이 체직을 청하다宣祖修正實錄 5책 22권宣祖修正實錄 25책",
    "date": "1588-04-01L0"
  },
  {
    "id": "wnb_12104001_002",
    "mainTitle": "윤국형을 부제학으로 삼다宣祖修正實錄 5책 22권宣祖修正實錄 25책",
    "date": "1588-04-01L0"
  },
  {
    "id": "wnb_12104001_003",
    "mainTitle": "검열 윤방이 사관은 정청하지 않기를 의논하다宣祖修正實錄 5책 22권宣祖修正實錄 25책",
    "date": "1588-04-01L0"
  },
  {
    "id": "wnb_12105001_001",
    "mainTitle": "다시 노수신을 영의정으로 삼다宣祖修正實錄 5책 22권宣祖修正實錄 25책",
    "date": "1588-05-01L0"
  },
  {
    "id": "wnb_12105001_002",
    "mainTitle": "알성시에서 황신 등 11인을 뽑다宣祖修正實錄 5책 22권宣祖修正實錄 25책",
    "date": "1588-05-01L0"
  },
  {
    "id": "wnb_12106001_001",
    "mainTitle": "영의정 노수신이 체직을 청함에 체직하고 판중추부사에 제수하다宣祖修正實錄 5책 22권宣祖修正實錄 25책",
    "date": "1588-06-01L0"
  },
  {
    "id": "wnb_12107001_001",
    "mainTitle": "지돈녕부사 안자유의 졸기宣祖修正實錄 5책 22권宣祖修正實錄 25책",
    "date": "1588-07-01L0"
  },
  {
    "id": "wnb_12108001_001",
    "mainTitle": "김성일을 종부시 첨정으로 삼다宣祖修正實錄 5책 22권宣祖修正實錄 25책",
    "date": "1588-08-01L0"
  },
  {
    "id": "wnb_12109001_001",
    "mainTitle": "우의정 정유길의 졸기宣祖修正實錄 5책 22권宣祖修正實錄 25책",
    "date": "1588-09-01L0"
  },
  {
    "id": "wnb_12110001_001",
    "mainTitle": "이산해를 우의정으로 삼다宣祖修正實錄 5책 22권宣祖修正實錄 25책",
    "date": "1588-10-01L0"
  },
  {
    "id": "wnb_12110001_002",
    "mainTitle": "유성룡을 형조 판서 겸 양관 대제학으로 삼다宣祖修正實錄 5책 22권宣祖修正實錄 25책",
    "date": "1588-10-01L0"
  },
  {
    "id": "wnb_12111001_001",
    "mainTitle": "형조 판서 김명원을 경기 감사, 김엽을 경상도 순찰사, 윤근수를 공조 참판으로 삼다宣祖修正實錄 5책 22권宣祖修正實錄 25책",
    "date": "1588-11-01L0"
  },
  {
    "id": "wnb_12112001_001",
    "mainTitle": "오억령·이호민·이항복·이덕형 등에게 관직을 제수하다宣祖修正實錄 5책 22권宣祖修正實錄 25책",
    "date": "1588-12-01L0"
  },
  {
    "id": "wnb_12112001_002",
    "mainTitle": "일본국 사신 평의지·현소가 내빙하다宣祖修正實錄 5책 22권宣祖修正實錄 25책",
    "date": "1588-12-01L0"
  }
]